Metadata-Version: 1.0
Name: mouzz
Version: 0.0.10
Summary: mouzz
Home-page: https://github.com/prim
Author: prim
Author-email: 1210102@qq.com
License: UNKNOWN
Platform: UNKNOWN
